[[{"id": 2, "nickname": "Mnelas", "age": 86, "sex": "m", "number_of_hours": 3103, "id_device": 390}], [{"id": 4, "nickname": "Sharpredeemer", "age": 60, "sex": "f", "number_of_hours": 3246, "id_device": 843}], [{"id": 5, "nickname": "Thunderforge", "age": 59, "sex": "m", "number_of_hours": 2598, "id_device": 913}], [{"id": 6, "nickname": "Bluefont", "age": 86, "sex": "m", "number_of_hours": 1627, "id_device": 316}], [{"id": 7, "nickname": "Kazrajin", "age": 75, "sex": "m", "number_of_hours": 2263, "id_device": 185}]]